becca_viz/LICENSE
becca_viz/__init__.py
becca_viz/actor_viz.py
becca_viz/affect_viz.py
becca_viz/feature_filter_viz.py
becca_viz/featurizer_viz.py
becca_viz/input_filter_viz.py
becca_viz/model_viz.py
becca_viz/postprocessor_viz.py
becca_viz/preprocessor_viz.py
becca_viz/viz.py
becca_viz/viz_tools.py
becca_viz/ziptie_viz.py
becca_viz-0.10.1.dist-info/METADATA
becca_viz-0.10.1.dist-info/RECORD
becca_viz-0.10.1.dist-info/WHEEL
becca_viz-0.10.1.dist-info/top_level.txt
